[
  {
    "answer": "YES",
    "timestamp": "2026-02-04T11:47:22.715499"
  },
  {
    "answer": "YES",
    "timestamp": "2026-02-04T11:47:25.186615"
  },
  {
    "answer": "YES",
    "timestamp": "2026-02-04T11:47:31.384221"
  },
  {
    "answer": "YES",
    "timestamp": "2026-02-04T11:47:32.160917"
  },
  {
    "answer": "YES",
    "timestamp": "2026-02-04T11:47:32.466760"
  },
  {
    "answer": "YES",
    "timestamp": "2026-02-04T11:50:23.700933"
  },
  {
    "answer": "YES",
    "timestamp": "2026-02-04T11:50:30.529852"
  },
  {
    "answer": "YES",
    "timestamp": "2026-02-04T11:51:05.269534"
  },
  {
    "answer": "YES",
    "timestamp": "2026-02-04T11:51:06.759093"
  },
  {
    "answer": "YES",
    "timestamp": "2026-02-04T11:51:06.960651"
  },
  {
    "answer": "YES",
    "timestamp": "2026-02-04T11:51:07.175604"
  },
  {
    "answer": "YES",
    "timestamp": "2026-02-04T11:55:16.404857"
  },
  {
    "answer": "YES",
    "timestamp": "2026-02-04T11:55:17.323837"
  },
  {
    "answer": "YES",
    "timestamp": "2026-02-04T12:15:07.815195"
  },
  {
    "answer": "YES",
    "timestamp": "2026-02-04T12:15:08.868219"
  },
  {
    "answer": "YES",
    "timestamp": "2026-02-04T12:28:29.810639"
  },
  {
    "answer": "YES",
    "timestamp": "2026-02-04T12:28:30.977950"
  },
  {
    "answer": "YES",
    "timestamp": "2026-02-04T12:28:31.360591"
  },
  {
    "answer": "YES",
    "timestamp": "2026-02-04T12:28:31.571549"
  },
  {
    "answer": "YES",
    "timestamp": "2026-02-04T12:28:31.812501"
  },
  {
    "answer": "YES",
    "timestamp": "2026-02-04T12:28:32.068813"
  },
  {
    "answer": "YES",
    "timestamp": "2026-02-04T12:28:32.272414"
  },
  {
    "answer": "YES",
    "timestamp": "2026-02-04T12:28:32.438920"
  },
  {
    "answer": "YES",
    "timestamp": "2026-02-04T12:28:32.641888"
  },
  {
    "answer": "YES",
    "timestamp": "2026-02-04T12:28:34.559714"
  },
  {
    "answer": "NO",
    "timestamp": "2026-02-04T12:28:34.947867"
  },
  {
    "answer": "NO",
    "timestamp": "2026-02-04T12:28:37.028882"
  },
  {
    "answer": "YES",
    "timestamp": "2026-02-04T12:28:37.710852"
  },
  {
    "answer": "NO",
    "timestamp": "2026-02-04T12:28:39.111538"
  },
  {
    "answer": "YES",
    "timestamp": "2026-02-04T12:28:39.651784"
  },
  {
    "answer": "YES",
    "timestamp": "2026-02-04T12:28:39.930853"
  },
  {
    "answer": "YES",
    "timestamp": "2026-02-04T12:28:40.127448"
  },
  {
    "answer": "YES",
    "timestamp": "2026-02-04T12:28:40.304686"
  },
  {
    "answer": "YES",
    "timestamp": "2026-02-04T12:28:40.531513"
  },
  {
    "answer": "YES",
    "timestamp": "2026-02-04T12:29:07.129913"
  },
  {
    "answer": "NO",
    "timestamp": "2026-02-04T12:29:09.093386"
  },
  {
    "answer": "YES",
    "timestamp": "2026-02-04T12:29:09.978150"
  },
  {
    "answer": "YES",
    "timestamp": "2026-02-04T12:29:14.789922"
  },
  {
    "answer": "YES",
    "timestamp": "2026-02-04T12:32:46.519403"
  },
  {
    "answer": "YES",
    "timestamp": "2026-02-04T12:37:42.692934"
  },
  {
    "answer": "NO",
    "timestamp": "2026-02-04T12:37:47.700749"
  }
]